AUTHORS
CHANGES
LICENSE
MANIFEST.in
README.md
requirements.txt
setup.py
giji_rtwo/__init__.py
giji_rtwo/compute.py
giji_rtwo/driver.py
giji_rtwo/exceptions.py
giji_rtwo/linktest.py
giji_rtwo/meta.py
giji_rtwo/settings.py
giji_rtwo/version.py
giji_rtwo.egg-info/PKG-INFO
giji_rtwo.egg-info/SOURCES.txt
giji_rtwo.egg-info/dependency_links.txt
giji_rtwo.egg-info/requires.txt
giji_rtwo.egg-info/top_level.txt
giji_rtwo/accounts/__init__.py
giji_rtwo/accounts/openstack.py
giji_rtwo/drivers/__init__.py
giji_rtwo/drivers/aws.py
giji_rtwo/drivers/common.py
giji_rtwo/drivers/eucalyptus.py
giji_rtwo/drivers/eucalyptus_user.py
giji_rtwo/drivers/irods_store.py
giji_rtwo/drivers/openstack_facade.py
giji_rtwo/drivers/openstack_network.py
giji_rtwo/drivers/openstack_user.py
giji_rtwo/mixins/__init__.py
giji_rtwo/mixins/driver.py
giji_rtwo/models/__init__.py
giji_rtwo/models/identity.py
giji_rtwo/models/instance.py
giji_rtwo/models/machine.py
giji_rtwo/models/provider.py
giji_rtwo/models/size.py
giji_rtwo/models/volume.py
giji_rtwo/test/__init__.py
giji_rtwo/test/test_openstack.py