Metadata-Version: 1.1
Name: giji-rtwo
Version: 0.1.1
Summary: A unified interface into multiple cloud providers.
Home-page: https://github.com/CCI-MOC/giji-rtwo
Author: MOC
Author-email: xuh@massopen.cloud
License: BSD License, 3 clause
Platform: UNKNOWN
Classifier: Development Status :: 4 - Beta
Classifier: Intended Audience :: Developers
Classifier: Intended Audience :: System Administrators
Classifier: Intended Audience :: Information Technology
Classifier: License :: OSI Approved :: BSD License
Classifier: Operating System :: OS Independent
Classifier: Programming Language :: Python
Classifier: Topic :: Software Development :: Libraries
Classifier: Topic :: System
Classifier: Topic :: System :: Clustering
Classifier: Topic :: System :: Distributed Computing
Classifier: Topic :: System :: Systems Administration
